{
    "valid_result": true,
    "email": "tanjimreza786@gmail.com",
    "profileDataArray": [
        {
            "SerialNo": 22,
            "NetflixEmail": "hange.zoe.ww@gmail.com",
            "AccountStart": "2024-01-20T18:15:00.000Z",
            "PackageName": "1 Screen",
            "ProfileName": "Tanjim-1",
            "Email": "tanjimreza786@gmail.com",
            "PaidAmount": 300,
            "StartDate": "2024-02-19T18:15:00.000Z",
            "PaidForDays": 30,
            "EndDate": "2024-03-20T18:15:00.000Z",
            "DaysLeft": -65,
            "DaysRunning": 95,
            "Contact": "AskRenew",
            "AccountEnds": "2024-02-19T18:15:00.000Z",
            "Remaining": 7272632,
            "Password": "REDUCTED",
            "AccountEmail": "hange.zoe.ww@gmail.com"
        },
        {
            "SerialNo": "",
            "NetflixEmail": "",
            "AccountStart": "Account Load Cost",
            "PackageName": "1 Screen",
            "ProfileName": "Tanjim-2",
            "Email": "tanjimreza786@gmail.com",
            "PaidAmount": 300,
            "StartDate": "2024-02-19T18:15:00.000Z",
            "PaidForDays": 30,
            "EndDate": "2024-03-20T18:15:00.000Z",
            "DaysLeft": -65,
            "DaysRunning": 95,
            "Contact": "AskRenew",
            "AccountEnds": "Account Profit",
            "Remaining": "",
            "Password": "REDUCTED",
            "AccountEmail": "hange.zoe.ww@gmail.com"
        },
        {
            "SerialNo": "",
            "NetflixEmail": "",
            "AccountStart": "",
            "PackageName": "1 Screen",
            "ProfileName": "Tanjim-3",
            "Email": "tanjimreza786@gmail.com",
            "PaidAmount": 300,
            "StartDate": "29-Jan-2024",
            "PaidForDays": 30,
            "EndDate": "2024-02-27T18:15:00.000Z",
            "DaysLeft": -87,
            "DaysRunning": 117,
            "Contact": "AskRenew",
            "AccountEnds": "",
            "Remaining": "",
            "Password": "REDUCTED",
            "AccountEmail": "hange.zoe.ww@gmail.com"
        },
        {
            "SerialNo": "",
            "NetflixEmail": "",
            "AccountStart": "Account Pass",
            "PackageName": "1 Screen",
            "ProfileName": "Tanijm-4",
            "Email": "tanjimreza786@gmail.com",
            "PaidAmount": 300,
            "StartDate": "2024-02-19T18:15:00.000Z",
            "PaidForDays": 30,
            "EndDate": "2024-03-20T18:15:00.000Z",
            "DaysLeft": -65,
            "DaysRunning": 95,
            "Contact": "AskRenew",
            "AccountEnds": "",
            "Remaining": "",
            "Password": "REDUCTED",
            "AccountEmail": "hange.zoe.ww@gmail.com"
        },
        {
            "SerialNo": "",
            "NetflixEmail": "VentureBITWW",
            "AccountStart": "Roshun212",
            "PackageName": "1 Screen",
            "ProfileName": "Mithila",
            "Email": "tanjimreza786@gmail.com",
            "PaidAmount": 300,
            "StartDate": "25-Jan-2024",
            "PaidForDays": 30,
            "EndDate": "2024-02-23T18:15:00.000Z",
            "DaysLeft": -91,
            "DaysRunning": 121,
            "Contact": "AskRenew",
            "AccountEnds": "",
            "Remaining": "",
            "Password": "REDUCTED",
            "AccountEmail": "hange.zoe.ww@gmail.com"
        }
    ]
}